deeppostagger
