Metadata-Version: 2.1
Name: deeppostagger
Version: 0.15
Summary: UNKNOWN
Home-page: https://github.com/sunkusun9/DeepPosTagger
Author: sun9sun9
Author-email: sun9sun9@gmail.com
License: UNKNOWN
Platform: UNKNOWN
